aBASEdzne/__init__.py
aBASEdzne/__main__.py
aBASEdzne/tests/__init__.py
aBASEdzne/tests/aBASE-output.xlsm
aBASEdzne/tests/test_1984.py
aBASEdzne-2.0.0.dev2.dist-info/LICENSE.txt
aBASEdzne-2.0.0.dev2.dist-info/METADATA
aBASEdzne-2.0.0.dev2.dist-info/WHEEL
aBASEdzne-2.0.0.dev2.dist-info/top_level.txt
aBASEdzne-2.0.0.dev2.dist-info/RECORD
