Metadata-Version: 2.1
Name: aBASEdzne
Version: 2.0.0.dev2
Summary: aBASEdzne
Author-email: Johannes <johannes-programming@mailfence.com>
License:                     GNU GENERAL PUBLIC LICENSE
Project-URL: Documentation, https://pypi.org/project/aBASEdzne
Project-URL: Download, https://pypi.org/project/aBASEdzne/#files
Project-URL: Source, https://github.com/johannes-programming/aBASEdzne
Classifier: Development Status :: 3 - Alpha
Classifier: License :: OSI Approved :: MIT License
Classifier: Programming Language :: Python
Classifier: Programming Language :: Python :: 3
Classifier: Programming Language :: Python :: 3 :: Only
Requires-Python: >=3.12.7
License-File: LICENSE.txt
Requires-Dist: BASEoriginaldata>=2.0.0.dev1
Requires-Dist: biopython==1.76
Requires-Dist: libBASE>=2.0.0.dev1
Requires-Dist: openpyxl==3.0.3
